lab/lab02-sumador4b/src_ise_basys/sum4b/sum1bcc.v
`timescale 1ns / 1ps
//////////////////////////////////////////////////////////////////////////////////
// Company: 
// Engineer: 
// 
// Create Date:    20:26:57 08/19/2019 
// Design Name: 
// Module Name:    sum1bcc 
// Project Name: 
// Target Devices: 
// Tool versions: 
// Description: 
//
// Dependencies: 
//
// Revision: 
// Revision 0.01 - File Created
// Additional Comments: 
//
//////////////////////////////////////////////////////////////////////////////////

module sum1bcc (A, B, Ci,Cout,S);

  input  A;
  input  B;
  input  Ci;
  output Cout;
  output S;

  wire [1:0] st;
  assign S = st[0];
  assign Cout = st[1];

  assign st  = 	A+B+Ci;
 
  
endmodule

lab/lab02-sumador4b/src_makefile/sum4b.v
`timescale 1ns / 1ps
//////////////////////////////////////////////////////////////////////////////////
// Company: 
// Engineer: 
// 
// Create Date:    20:20:31 08/19/2019 
// Design Name: 
// Module Name:    sum4b 
// Project Name: 
// Target Devices: 
// Tool versions: 
// Description: 
//
// Dependencies: 
//
// Revision: 
// Revision 0.01 - File Created
// Additional Comments: 
//
//////////////////////////////////////////////////////////////////////////////////
module sum4b(xi, yi,co,zi);


  input [3 :0] xi;
  input [3 :0] yi;
  output co;
  output [3 :0] zi;

  wire c1,c2,c3;
  sum1bcc s0 (.A(xi[0]), .B(yi[0]), .Ci(0),  .Cout(c1) ,.S(zi[0]));
  sum1bcc s1 (.A(xi[1]), .B(yi[1]), .Ci(c1), .Cout(c2) ,.S(zi[1]));
  sum1bcc s2 (.A(xi[2]), .B(yi[2]), .Ci(c2), .Cout(c3) ,.S(zi[2]));
  sum1bcc s3 (.A(xi[3]), .B(yi[3]), .Ci(c3), .Cout(co) ,.S(zi[3]));



endmodule

lab/lab02-sumador4b/src_makefile/sum4b_TB.v
`timescale 1ns / 1ps

module sum4b_TB;

  // Inputs
  reg [3:0] xi;
  reg [3:0] yi;

  // Outputs
  wire co;
  wire [3:0] zi;

  // Instantiate the Unit Under Test (UUT)
  sum4b uut (
    .xi(xi), 
    .yi(yi), 
    .co(co), 
    .zi(zi)
  );

  initial begin
  // Initialize Inputs
    xi=0;
	 for (yi = 0; yi < 16; yi = yi + 1) begin
      if (yi==0)
        xi=xi+1;
      #5 $display("el valor de %d + %d = %d", xi,yi,zi) ;
    end
  end      


initial begin: TEST_CASE
     $dumpfile("sum4b_TB.vcd");
     $dumpvars(-1, uut);
     #(1280) $finish;
   end

endmodule

lab/lab02-sumador4b/src_makefile/simulation/sum4b_TB.vcd
$date
	Wed Aug 21 17:14:28 2019
$end
$version
	Icarus Verilog
$end
$timescale
	1ps
$end
$scope module sum4b_TB $end
$scope module uut $end
$var wire 4 ! xi [3:0] $end
$var wire 4 " yi [3:0] $end
$var wire 4 # zi [3:0] $end
$var wire 1 $ co $end
$var wire 1 % c3 $end
$var wire 1 & c2 $end
$var wire 1 ' c1 $end
$scope module s0 $end
$var wire 1 ( A $end
$var wire 1 ) B $end
$var wire 1 * Ci $end
$var wire 2 + st [1:0] $end
$var wire 1 , S $end
$var wire 1 ' Cout $end
$upscope $end
$scope module s1 $end
$var wire 1 - A $end
$var wire 1 . B $end
$var wire 1 ' Ci $end
$var wire 2 / st [1:0] $end
$var wire 1 0 S $end
$var wire 1 & Cout $end
$upscope $end
$scope module s2 $end
$var wire 1 1 A $end
$var wire 1 2 B $end
$var wire 1 & Ci $end
$var wire 2 3 st [1:0] $end
$var wire 1 4 S $end
$var wire 1 % Cout $end
$upscope $end
$scope module s3 $end
$var wire 1 5 A $end
$var wire 1 6 B $end
$var wire 1 % Ci $end
$var wire 2 7 st [1:0] $end
$var wire 1 8 S $end
$var wire 1 $ Cout $end
$upscope $end
$upscope $end
$upscope $end
$enddefinitions $end
#0
$dumpvars
08
b0 7
06
05
04
b0 3
02
01
00
b0 /
0.
0-
1,
b1 +
0*
0)
1(
0'
0&
0%
0$
b1 #
b0 "
b1 !
$end
#5000
10
b1 /
1'
b10 #
0,
b10 +
1)
b1 "
#10000
04
0'
1,
b0 3
0&
b11 #
10
b1 +
0)
b1 /
1.
b10 "
#15000
14
b1 3
1&
00
b10 /
1'
b100 #
0,
b10 +
1)
b11 "
#20000
08
0'
1,
0&
00
b0 7
0%
b101 #
14
b1 +
0)
b0 /
0.
b1 3
12
b100 "
#25000
10
b1 /
1'
b110 #
0,
b10 +
1)
b101 "
#30000
08
b0 7
0%
14
0'
1,
b1 3
0&
b111 #
10
b1 +
0)
b1 /
1.
b110 "
#35000
18
b1 7
1%
04
b10 3
1&
00
b10 /
1'
b1000 #
0,
b10 +
1)
b111 "
#40000
0'
1,
0&
00
0%
04
0$
b1001 #
18
b1 +
0)
b0 /
0.
b0 3
02
b1 7
16
b1000 "
#45000
10
b1 /
1'
b1010 #
0,
b10 +
1)
b1001 "
#50000
04
0'
1,
b0 3
0&
b1011 #
10
b1 +
0)
b1 /
1.
b1010 "
#55000
14
b1 3
1&
00
b10 /
1'
b1100 #
0,
b10 +
1)
b1011 "
#60000
0$
18
0'
1,
0&
00
b1 7
0%
b1101 #
14
b1 +
0)
b0 /
0.
b1 3
12
b1100 "
#65000
10
b1 /
1'
b1110 #
0,
b10 +
1)
b1101 "
#70000
0$
18
b1 7
0%
14
0'
1,
b1 3
0&
b1111 #
10
b1 +
0)
b1 /
1.
b1110 "
#75000
1$
08
b10 7
1%
04
b10 3
1&
00
b10 /
1'
b0 #
0,
b10 +
1)
b1111 "
#80000
0&
10
0'
0%
04
0$
b10 #
08
0(
1-
b0 +
0)
b1 /
0.
b0 3
02
b0 7
06
b10 !
b0 "
#85000
b11 #
1,
b1 +
1)
b1 "
#90000
14
0,
b1 3
1&
b100 #
00
b0 +
0)
b10 /
1.
b10 "
#95000
b101 #
1,
b1 +
1)
b11 "
#100000
08
0,
0&
10
b0 7
0%
b110 #
14
b0 +
0)
b1 /
0.
b1 3
12
b100 "
#105000
b111 #
1,
b1 +
1)
b101 "
#110000
18
b1 7
1%
04
0,
b10 3
1&
b1000 #
00
b0 +
0)
b10 /
1.
b110 "
#115000
b1001 #
1,
b1 +
1)
b111 "
#120000
0,
0&
10
0%
04
0$
b1010 #
18
b0 +
0)
b1 /
0.
b0 3
02
b1 7
16
b1000 "
#125000
b1011 #
1,
b1 +
1)
b1001 "
#130000
14
0,
b1 3
1&
b1100 #
00
b0 +
0)
b10 /
1.
b1010 "
#135000
b1101 #
1,
b1 +
1)
b1011 "
#140000
0$
18
0,
0&
10
b1 7
0%
b1110 #
14
b0 +
0)
b1 /
0.
b1 3
12
b1100 "
#145000
b1111 #
1,
b1 +
1)
b1101 "
#150000
1$
08
b10 7
1%
04
0,
b10 3
1&
b0 #
00
b0 +
0)
b10 /
1.
b1110 "
#155000
b1 #
1,
b1 +
1)
b1111 "
#160000
0&
10
0%
04
0$
b11 #
08
1(
b1 +
0)
b1 /
0.
b0 3
02
b0 7
06
b11 !
b0 "
#165000
14
b1 3
1&
00
b10 /
1'
b100 #
0,
b10 +
1)
b1 "
#170000
0'
1,
b101 #
00
b1 +
0)
b10 /
1.
b10 "
#175000
10
b11 /
1'
b110 #
0,
b10 +
1)
b11 "
#180000
0&
08
0'
1,
10
b0 7
0%
b111 #
14
b1 +
0)
b1 /
0.
b1 3
12
b100 "
#185000
18
b1 7
1%
04
b10 3
1&
00
b10 /
1'
b1000 #
0,
b10 +
1)
b101 "
#190000
0'
1,
b1001 #
00
b1 +
0)
b10 /
1.
b110 "
#195000
10
b11 /
1'
b1010 #
0,
b10 +
1)
b111 "
#200000
0&
0'
1,
10
0%
04
0$
b1011 #
18
b1 +
0)
b1 /
0.
b0 3
02
b1 7
16
b1000 "
#205000
14
b1 3
1&
00
b10 /
1'
b1100 #
0,
b10 +
1)
b1001 "
#210000
0'
1,
b1101 #
00
b1 +
0)
b10 /
1.
b1010 "
#215000
10
b11 /
1'
b1110 #
0,
b10 +
1)
b1011 "
#220000
0&
0$
18
0'
1,
10
b1 7
0%
b1111 #
14
b1 +
0)
b1 /
0.
b1 3
12
b1100 "
#225000
1$
08
b10 7
1%
04
b10 3
1&
00
b10 /
1'
b0 #
0,
b10 +
1)
b1101 "
#230000
0'
1,
b1 #
00
b1 +
0)
b10 /
1.
b1110 "
#235000
10
b11 /
1'
b10 #
0,
b10 +
1)
b1111 "
#240000
0%
14
00
0&
0'
0$
b100 #
08
0(
0-
11
b0 +
0)
b0 /
0.
b1 3
02
b0 7
06
b100 !
b0 "
#245000
b101 #
1,
b1 +
1)
b1 "
#250000
0,
b110 #
10
b0 +
0)
b1 /
1.
b10 "
#255000
b111 #
1,
b1 +
1)
b11 "
#260000
18
0,
00
b1 7
1%
b1000 #
04
b0 +
0)
b0 /
0.
b10 3
12
b100 "
#265000
b1001 #
1,
b1 +
1)
b101 "
#270000
0,
b1010 #
10
b0 +
0)
b1 /
1.
b110 "
#275000
b1011 #
1,
b1 +
1)
b111 "
#280000
0,
00
0%
14
0$
b1100 #
18
b0 +
0)
b0 /
0.
b1 3
02
b1 7
16
b1000 "
#285000
b1101 #
1,
b1 +
1)
b1001 "
#290000
0,
b1110 #
10
b0 +
0)
b1 /
1.
b1010 "
#295000
b1111 #
1,
b1 +
1)
b1011 "
#300000
1$
08
0,
00
b10 7
1%
b0 #
04
b0 +
0)
b0 /
0.
b10 3
12
b1100 "
#305000
b1 #
1,
b1 +
1)
b1101 "
#310000
0,
b10 #
10
b0 +
0)
b1 /
1.
b1110 "
#315000
b11 #
1,
b1 +
1)
b1111 "
#320000
00
0%
14
0$
b101 #
08
1(
b1 +
0)
b0 /
0.
b1 3
02
b0 7
06
b101 !
b0 "
#325000
10
b1 /
1'
b110 #
0,
b10 +
1)
b1 "
#330000
08
b0 7
0%
14
0'
1,
b1 3
0&
b111 #
10
b1 +
0)
b1 /
1.
b10 "
#335000
18
b1 7
1%
04
b10 3
1&
00
b10 /
1'
b1000 #
0,
b10 +
1)
b11 "
#340000
0'
1,
0&
00
b1001 #
04
b1 +
0)
b0 /
0.
b10 3
12
b100 "
#345000
10
b1 /
1'
b1010 #
0,
b10 +
1)
b101 "
#350000
04
0'
1,
b10 3
0&
b1011 #
10
b1 +
0)
b1 /
1.
b110 "
#355000
14
b11 3
1&
00
b10 /
1'
b1100 #
0,
b10 +
1)
b111 "
#360000
0%
0'
1,
0&
00
14
0$
b1101 #
18
b1 +
0)
b0 /
0.
b1 3
02
b1 7
16
b1000 "
#365000
10
b1 /
1'
b1110 #
0,
b10 +
1)
b1001 "
#370000
0$
18
b1 7
0%
14
0'
1,
b1 3
0&
b1111 #
10
b1 +
0)
b1 /
1.
b1010 "
#375000
1$
08
b10 7
1%
04
b10 3
1&
00
b10 /
1'
b0 #
0,
b10 +
1)
b1011 "
#380000
0'
1,
0&
00
b1 #
04
b1 +
0)
b0 /
0.
b10 3
12
b1100 "
#385000
10
b1 /
1'
b10 #
0,
b10 +
1)
b1101 "
#390000
04
0'
1,
b10 3
0&
b11 #
10
b1 +
0)
b1 /
1.
b1110 "
#395000
14
b11 3
1&
00
b10 /
1'
b100 #
0,
b10 +
1)
b1111 "
#400000
0%
0&
10
0'
14
0$
b110 #
08
0(
1-
b0 +
0)
b1 /
0.
b1 3
02
b0 7
06
b110 !
b0 "
#405000
b111 #
1,
b1 +
1)
b1 "
#410000
18
b1 7
1%
04
0,
b10 3
1&
b1000 #
00
b0 +
0)
b10 /
1.
b10 "
#415000
b1001 #
1,
b1 +
1)
b11 "
#420000
0,
0&
10
b1010 #
04
b0 +
0)
b1 /
0.
b10 3
12
b100 "
#425000
b1011 #
1,
b1 +
1)
b101 "
#430000
14
0,
b11 3
1&
b1100 #
00
b0 +
0)
b10 /
1.
b110 "
#435000
b1101 #
1,
b1 +
1)
b111 "
#440000
0%
0,
0&
10
14
0$
b1110 #
18
b0 +
0)
b1 /
0.
b1 3
02
b1 7
16
b1000 "
#445000
b1111 #
1,
b1 +
1)
b1001 "
#450000
1$
08
b10 7
1%
04
0,
b10 3
1&
b0 #
00
b0 +
0)
b10 /
1.
b1010 "
#455000
b1 #
1,
b1 +
1)
b1011 "
#460000
0,
0&
10
b10 #
04
b0 +
0)
b1 /
0.
b10 3
12
b1100 "
#465000
b11 #
1,
b1 +
1)
b1101 "
#470000
14
0,
b11 3
1&
b100 #
00
b0 +
0)
b10 /
1.
b1110 "
#475000
b101 #
1,
b1 +
1)
b1111 "
#480000
0%
0&
10
14
0$
b111 #
08
1(
b1 +
0)
b1 /
0.
b1 3
02
b0 7
06
b111 !
b0 "
#485000
18
b1 7
1%
04
b10 3
1&
00
b10 /
1'
b1000 #
0,
b10 +
1)
b1 "
#490000
0'
1,
b1001 #
00
b1 +
0)
b10 /
1.
b10 "
#495000
10
b11 /
1'
b1010 #
0,
b10 +
1)
b11 "
#500000
0&
0'
1,
10
b1011 #
04
b1 +
0)
b1 /
0.
b10 3
12
b100 "
#505000
14
b11 3
1&
00
b10 /
1'
b1100 #
0,
b10 +
1)
b101 "
#510000
0'
1,
b1101 #
00
b1 +
0)
b10 /
1.
b110 "
#515000
10
b11 /
1'
b1110 #
0,
b10 +
1)
b111 "
#520000
0%
0&
0'
1,
10
14
0$
b1111 #
18
b1 +
0)
b1 /
0.
b1 3
02
b1 7
16
b1000 "
#525000
1$
08
b10 7
1%
04
b10 3
1&
00
b10 /
1'
b0 #
0,
b10 +
1)
b1001 "
#530000
0'
1,
b1 #
00
b1 +
0)
b10 /
1.
b1010 "
#535000
10
b11 /
1'
b10 #
0,
b10 +
1)
b1011 "
#540000
0&
0'
1,
10
b11 #
04
b1 +
0)
b1 /
0.
b10 3
12
b1100 "
#545000
14
b11 3
1&
00
b10 /
1'
b100 #
0,
b10 +
1)
b1101 "
#550000
0'
1,
b101 #
00
b1 +
0)
b10 /
1.
b1110 "
#555000
10
b11 /
1'
b110 #
0,
b10 +
1)
b1111 "
#560000
04
0$
18
b1000 #
00
0&
0%
0'
0(
0-
01
15
b0 +
0)
b0 /
0.
b0 3
02
b1 7
06
b1000 !
b0 "
#565000
b1001 #
1,
b1 +
1)
b1 "
#570000
0,
b1010 #
10
b0 +
0)
b1 /
1.
b10 "
#575000
b1011 #
1,
b1 +
1)
b11 "
#580000
0,
00
b1100 #
14
b0 +
0)
b0 /
0.
b1 3
12
b100 "
#585000
b1101 #
1,
b1 +
1)
b101 "
#590000
0,
b1110 #
10
b0 +
0)
b1 /
1.
b110 "
#595000
b1111 #
1,
b1 +
1)
b111 "
#600000
0,
00
04
1$
b0 #
08
b0 +
0)
b0 /
0.
b0 3
02
b10 7
16
b1000 "
#605000
b1 #
1,
b1 +
1)
b1001 "
#610000
0,
b10 #
10
b0 +
0)
b1 /
1.
b1010 "
#615000
b11 #
1,
b1 +
1)
b1011 "
#620000
0,
00
b100 #
14
b0 +
0)
b0 /
0.
b1 3
12
b1100 "
#625000
b101 #
1,
b1 +
1)
b1101 "
#630000
0,
b110 #
10
b0 +
0)
b1 /
1.
b1110 "
#635000
b111 #
1,
b1 +
1)
b1111 "
#640000
00
04
0$
b1001 #
18
1(
b1 +
0)
b0 /
0.
b0 3
02
b1 7
06
b1001 !
b0 "
#645000
10
b1 /
1'
b1010 #
0,
b10 +
1)
b1 "
#650000
04
0'
1,
b0 3
0&
b1011 #
10
b1 +
0)
b1 /
1.
b10 "
#655000
14
b1 3
1&
00
b10 /
1'
b1100 #
0,
b10 +
1)
b11 "
#660000
0$
18
0'
1,
0&
00
b1 7
0%
b1101 #
14
b1 +
0)
b0 /
0.
b1 3
12
b100 "
#665000
10
b1 /
1'
b1110 #
0,
b10 +
1)
b101 "
#670000
0$
18
b1 7
0%
14
0'
1,
b1 3
0&
b1111 #
10
b1 +
0)
b1 /
1.
b110 "
#675000
1$
08
b10 7
1%
04
b10 3
1&
00
b10 /
1'
b0 #
0,
b10 +
1)
b111 "
#680000
0'
1,
0&
00
0%
04
b1 #
08
b1 +
0)
b0 /
0.
b0 3
02
b10 7
16
b1000 "
#685000
10
b1 /
1'
b10 #
0,
b10 +
1)
b1001 "
#690000
04
0'
1,
b0 3
0&
b11 #
10
b1 +
0)
b1 /
1.
b1010 "
#695000
14
b1 3
1&
00
b10 /
1'
b100 #
0,
b10 +
1)
b1011 "
#700000
08
0'
1,
0&
00
b10 7
0%
b101 #
14
b1 +
0)
b0 /
0.
b1 3
12
b1100 "
#705000
10
b1 /
1'
b110 #
0,
b10 +
1)
b1101 "
#710000
08
b10 7
0%
14
0'
1,
b1 3
0&
b111 #
10
b1 +
0)
b1 /
1.
b1110 "
#715000
18
b11 7
1%
04
b10 3
1&
00
b10 /
1'
b1000 #
0,
b10 +
1)
b1111 "
#720000
0&
10
0$
0'
0%
04
b1010 #
18
0(
1-
b0 +
0)
b1 /
0.
b0 3
02
b1 7
06
b1010 !
b0 "
#725000
b1011 #
1,
b1 +
1)
b1 "
#730000
14
0,
b1 3
1&
b1100 #
00
b0 +
0)
b10 /
1.
b10 "
#735000
b1101 #
1,
b1 +
1)
b11 "
#740000
0$
18
0,
0&
10
b1 7
0%
b1110 #
14
b0 +
0)
b1 /
0.
b1 3
12
b100 "
#745000
b1111 #
1,
b1 +
1)
b101 "
#750000
1$
08
b10 7
1%
04
0,
b10 3
1&
b0 #
00
b0 +
0)
b10 /
1.
b110 "
#755000
b1 #
1,
b1 +
1)
b111 "
#760000
0,
0&
10
0%
04
b10 #
08
b0 +
0)
b1 /
0.
b0 3
02
b10 7
16
b1000 "
#765000
b11 #
1,
b1 +
1)
b1001 "
#770000
14
0,
b1 3
1&
b100 #
00
b0 +
0)
b10 /
1.
b1010 "
#775000
b101 #
1,
b1 +
1)
b1011 "
#780000
08
0,
0&
10
b10 7
0%
b110 #
14
b0 +
0)
b1 /
0.
b1 3
12
b1100 "
#785000
b111 #
1,
b1 +
1)
b1101 "
#790000
18
b11 7
1%
04
0,
b10 3
1&
b1000 #
00
b0 +
0)
b10 /
1.
b1110 "
#795000
b1001 #
1,
b1 +
1)
b1111 "
#800000
0$
0&
10
0%
04
b1011 #
18
1(
b1 +
0)
b1 /
0.
b0 3
02
b1 7
06
b1011 !
b0 "
#805000
14
b1 3
1&
00
b10 /
1'
b1100 #
0,
b10 +
1)
b1 "
#810000
0'
1,
b1101 #
00
b1 +
0)
b10 /
1.
b10 "
#815000
10
b11 /
1'
b1110 #
0,
b10 +
1)
b11 "
#820000
0&
0$
18
0'
1,
10
b1 7
0%
b1111 #
14
b1 +
0)
b1 /
0.
b1 3
12
b100 "
#825000
1$
08
b10 7
1%
04
b10 3
1&
00
b10 /
1'
b0 #
0,
b10 +
1)
b101 "
#830000
0'
1,
b1 #
00
b1 +
0)
b10 /
1.
b110 "
#835000
10
b11 /
1'
b10 #
0,
b10 +
1)
b111 "
#840000
0&
0'
1,
10
0%
04
b11 #
08
b1 +
0)
b1 /
0.
b0 3
02
b10 7
16
b1000 "
#845000
14
b1 3
1&
00
b10 /
1'
b100 #
0,
b10 +
1)
b1001 "
#850000
0'
1,
b101 #
00
b1 +
0)
b10 /
1.
b1010 "
#855000
10
b11 /
1'
b110 #
0,
b10 +
1)
b1011 "
#860000
0&
08
0'
1,
10
b10 7
0%
b111 #
14
b1 +
0)
b1 /
0.
b1 3
12
b1100 "
#865000
18
b11 7
1%
04
b10 3
1&
00
b10 /
1'
b1000 #
0,
b10 +
1)
b1101 "
#870000
0'
1,
b1001 #
00
b1 +
0)
b10 /
1.
b1110 "
#875000
10
b11 /
1'
b1010 #
0,
b10 +
1)
b1111 "
#880000
0$
0%
14
00
0&
0'
b1100 #
18
0(
0-
11
b0 +
0)
b0 /
0.
b1 3
02
b1 7
06
b1100 !
b0 "
#885000
b1101 #
1,
b1 +
1)
b1 "
#890000
0,
b1110 #
10
b0 +
0)
b1 /
1.
b10 "
#895000
b1111 #
1,
b1 +
1)
b11 "
#900000
1$
08
0,
00
b10 7
1%
b0 #
04
b0 +
0)
b0 /
0.
b10 3
12
b100 "
#905000
b1 #
1,
b1 +
1)
b101 "
#910000
0,
b10 #
10
b0 +
0)
b1 /
1.
b110 "
#915000
b11 #
1,
b1 +
1)
b111 "
#920000
0,
00
0%
14
b100 #
08
b0 +
0)
b0 /
0.
b1 3
02
b10 7
16
b1000 "
#925000
b101 #
1,
b1 +
1)
b1001 "
#930000
0,
b110 #
10
b0 +
0)
b1 /
1.
b1010 "
#935000
b111 #
1,
b1 +
1)
b1011 "
#940000
18
0,
00
b11 7
1%
b1000 #
04
b0 +
0)
b0 /
0.
b10 3
12
b1100 "
#945000
b1001 #
1,
b1 +
1)
b1101 "
#950000
0,
b1010 #
10
b0 +
0)
b1 /
1.
b1110 "
#955000
b1011 #
1,
b1 +
1)
b1111 "
#960000
0$
00
0%
14
b1101 #
18
1(
b1 +
0)
b0 /
0.
b1 3
02
b1 7
06
b1101 !
b0 "
#965000
10
b1 /
1'
b1110 #
0,
b10 +
1)
b1 "
#970000
0$
18
b1 7
0%
14
0'
1,
b1 3
0&
b1111 #
10
b1 +
0)
b1 /
1.
b10 "
#975000
1$
08
b10 7
1%
04
b10 3
1&
00
b10 /
1'
b0 #
0,
b10 +
1)
b11 "
#980000
0'
1,
0&
00
b1 #
04
b1 +
0)
b0 /
0.
b10 3
12
b100 "
#985000
10
b1 /
1'
b10 #
0,
b10 +
1)
b101 "
#990000
04
0'
1,
b10 3
0&
b11 #
10
b1 +
0)
b1 /
1.
b110 "
#995000
14
b11 3
1&
00
b10 /
1'
b100 #
0,
b10 +
1)
b111 "
#1000000
0%
0'
1,
0&
00
14
b101 #
08
b1 +
0)
b0 /
0.
b1 3
02
b10 7
16
b1000 "
#1005000
10
b1 /
1'
b110 #
0,
b10 +
1)
b1001 "
#1010000
08
b10 7
0%
14
0'
1,
b1 3
0&
b111 #
10
b1 +
0)
b1 /
1.
b1010 "
#1015000
18
b11 7
1%
04
b10 3
1&
00
b10 /
1'
b1000 #
0,
b10 +
1)
b1011 "
#1020000
0'
1,
0&
00
b1001 #
04
b1 +
0)
b0 /
0.
b10 3
12
b1100 "
#1025000
10
b1 /
1'
b1010 #
0,
b10 +
1)
b1101 "
#1030000
04
0'
1,
b10 3
0&
b1011 #
10
b1 +
0)
b1 /
1.
b1110 "
#1035000
14
b11 3
1&
00
b10 /
1'
b1100 #
0,
b10 +
1)
b1111 "
#1040000
0$
0%
0&
10
0'
14
b1110 #
18
0(
1-
b0 +
0)
b1 /
0.
b1 3
02
b1 7
06
b1110 !
b0 "
#1045000
b1111 #
1,
b1 +
1)
b1 "
#1050000
1$
08
b10 7
1%
04
0,
b10 3
1&
b0 #
00
b0 +
0)
b10 /
1.
b10 "
#1055000
b1 #
1,
b1 +
1)
b11 "
#1060000
0,
0&
10
b10 #
04
b0 +
0)
b1 /
0.
b10 3
12
b100 "
#1065000
b11 #
1,
b1 +
1)
b101 "
#1070000
14
0,
b11 3
1&
b100 #
00
b0 +
0)
b10 /
1.
b110 "
#1075000
b101 #
1,
b1 +
1)
b111 "
#1080000
0%
0,
0&
10
14
b110 #
08
b0 +
0)
b1 /
0.
b1 3
02
b10 7
16
b1000 "
#1085000
b111 #
1,
b1 +
1)
b1001 "
#1090000
18
b11 7
1%
04
0,
b10 3
1&
b1000 #
00
b0 +
0)
b10 /
1.
b1010 "
#1095000
b1001 #
1,
b1 +
1)
b1011 "
#1100000
0,
0&
10
b1010 #
04
b0 +
0)
b1 /
0.
b10 3
12
b1100 "
#1105000
b1011 #
1,
b1 +
1)
b1101 "
#1110000
14
0,
b11 3
1&
b1100 #
00
b0 +
0)
b10 /
1.
b1110 "
#1115000
b1101 #
1,
b1 +
1)
b1111 "
#1120000
0$
0%
0&
10
14
b1111 #
18
1(
b1 +
0)
b1 /
0.
b1 3
02
b1 7
06
b1111 !
b0 "
#1125000
1$
08
b10 7
1%
04
b10 3
1&
00
b10 /
1'
b0 #
0,
b10 +
1)
b1 "
#1130000
0'
1,
b1 #
00
b1 +
0)
b10 /
1.
b10 "
#1135000
10
b11 /
1'
b10 #
0,
b10 +
1)
b11 "
#1140000
0&
0'
1,
10
b11 #
04
b1 +
0)
b1 /
0.
b10 3
12
b100 "
#1145000
14
b11 3
1&
00
b10 /
1'
b100 #
0,
b10 +
1)
b101 "
#1150000
0'
1,
b101 #
00
b1 +
0)
b10 /
1.
b110 "
#1155000
10
b11 /
1'
b110 #
0,
b10 +
1)
b111 "
#1160000
0%
0&
0'
1,
10
14
b111 #
08
b1 +
0)
b1 /
0.
b1 3
02
b10 7
16
b1000 "
#1165000
18
b11 7
1%
04
b10 3
1&
00
b10 /
1'
b1000 #
0,
b10 +
1)
b1001 "
#1170000
0'
1,
b1001 #
00
b1 +
0)
b10 /
1.
b1010 "
#1175000
10
b11 /
1'
b1010 #
0,
b10 +
1)
b1011 "
#1180000
0&
0'
1,
10
b1011 #
04
b1 +
0)
b1 /
0.
b10 3
12
b1100 "
#1185000
14
b11 3
1&
00
b10 /
1'
b1100 #
0,
b10 +
1)
b1101 "
#1190000
0'
1,
b1101 #
00
b1 +
0)
b10 /
1.
b1110 "
#1195000
10
b11 /
1'
b1110 #
0,
b10 +
1)
b1111 "
#1200000
04
08
b0 #
00
0&
0%
0$
0'
0(
0-
01
05
b0 +
0)
b0 /
0.
b0 3
02
b0 7
06
b0 !
b0 "
#1205000
b1 #
1,
b1 +
1)
b1 "
#1210000
0,
b10 #
10
b0 +
0)
b1 /
1.
b10 "
#1215000
b11 #
1,
b1 +
1)
b11 "
#1220000
0,
00
b100 #
14
b0 +
0)
b0 /
0.
b1 3
12
b100 "
#1225000
b101 #
1,
b1 +
1)
b101 "
#1230000
0,
b110 #
10
b0 +
0)
b1 /
1.
b110 "
#1235000
b111 #
1,
b1 +
1)
b111 "
#1240000
0,
00
04
b1000 #
18
b0 +
0)
b0 /
0.
b0 3
02
b1 7
16
b1000 "
#1245000
b1001 #
1,
b1 +
1)
b1001 "
#1250000
0,
b1010 #
10
b0 +
0)
b1 /
1.
b1010 "
#1255000
b1011 #
1,
b1 +
1)
b1011 "
#1260000
0,
00
b1100 #
14
b0 +
0)
b0 /
0.
b1 3
12
b1100 "
#1265000
b1101 #
1,
b1 +
1)
b1101 "
#1270000
0,
b1110 #
10
b0 +
0)
b1 /
1.
b1110 "
#1275000
b1111 #
1,
b1 +
1)
b1111 "
