lab/lab01-sumador1b/src/sum1bcc_primitive.v
module sum1bcc_primitive (A, B, Ci,Cout,S);

  input  A;
  input  B;
  input  Ci;
  output Cout;
  output S;


  wire a_ab;
  wire x_ab;
  wire cout_t;

  and(a_ab,A,B);
  xor(x_ab,A,B);

  xor(S,x_ab,Ci);
  and(cout_t,x_ab,Ci);

  or (Cout,cout_t,a_ab);
endmodule

lab/lab01-sumador1b/src/sum1bcc_primitive_TB.v
module sum1bcc_primitive_TB;

  reg x;
  reg y;
  reg c;
  wire out;
  wire z;


sum1bcc_primitive uut(x, y, c,out,z);


initial begin
x=0; y=0; c=0; #3;
x=0; y=0; c=1; #3;
x=0; y=1; c=0; #3;
x=0; y=1; c=1; #3;
x=1; y=0; c=0; #3;
x=1; y=0; c=1; #3;
x=1; y=1; c=0; #3;
x=1; y=1; c=1; #3;



end

initial begin: TEST_CASE
     $dumpfile("sum1bcc_primitive_TB.vcd");
     $dumpvars(-1, uut);
     #(200) $finish;
   end

endmodule //

lab/lab01-sumador1b/src/simulation/sum1bcc_primitive_TB.vcd
$date
	Mon Aug 12 17:03:18 2019
$end
$version
	Icarus Verilog
$end
$timescale
	1s
$end
$scope module sum1bcc_primitive_TB $end
$scope module uut $end
$var wire 1 ! A $end
$var wire 1 " B $end
$var wire 1 # Ci $end
$var wire 1 $ Cout $end
$var wire 1 % S $end
$var wire 1 & a_ab $end
$var wire 1 ' cout_t $end
$var wire 1 ( x_ab $end
$upscope $end
$upscope $end
$enddefinitions $end
#0
$dumpvars
0(
0'
0&
0%
0$
0#
0"
0!
$end
#3
1%
1#
#6
1(
0#
1"
#9
1$
0%
1'
1#
#12
0$
1%
0'
0#
0"
1!
#15
1$
0%
1'
1#
#18
0'
1&
0(
0#
1"
#21
1%
1#
